pyminitab/__init__.py
pyminitab/main.py
pyminitab-0.6.0.dist-info/METADATA
pyminitab-0.6.0.dist-info/WHEEL
pyminitab-0.6.0.dist-info/RECORD
